lavatory/__init__.py
lavatory/__main__.py
lavatory/consts.py
lavatory/credentials.py
lavatory/exceptions.py
lavatory/commands/__init__.py
lavatory/commands/policies.py
lavatory/commands/purge.py
lavatory/commands/stats.py
lavatory/policies/__init__.py
lavatory/policies/default.py
lavatory/utils/__init__.py
lavatory/utils/artifactory.py
lavatory/utils/get_artifactory_info.py
lavatory/utils/performance.py
lavatory/utils/setup_pluginbase.py
lavatory-1.2.2.dist-info/LICENSE
lavatory-1.2.2.dist-info/METADATA
lavatory-1.2.2.dist-info/WHEEL
lavatory-1.2.2.dist-info/entry_points.txt
lavatory-1.2.2.dist-info/top_level.txt
lavatory-1.2.2.dist-info/RECORD
