Metadata-Version: 2.1
Name: lavatory
Version: 1.2.2
Summary: Run retention policies against Artifactory repositories
Home-page: https://github.com/gogoair/lavatory
Author: Gogo DevOps
Author-email: ps-devops-tooling@example.com
License: Apache License (2.0)
Download-URL: https://github.com/gogoair/lavatory
Keywords: gogo infrastructure python artifactory jfrog
Platform: OS Independent
Classifier: Development Status :: 5 - Production/Stable
Classifier: Intended Audience :: Developers
Classifier: Programming Language :: Python :: 3.5
Classifier: Programming Language :: Python :: 3.6
Classifier: Programming Language :: Python :: 3.7
Classifier: License :: OSI Approved :: Apache Software License
Classifier: Operating System :: OS Independent
Requires-Dist: pip
Requires-Dist: click
Requires-Dist: coloredlogs
Requires-Dist: certifi
Requires-Dist: requests
Requires-Dist: humanfriendly
Requires-Dist: party
Requires-Dist: pluginbase
